minecraftinfo/__init__.py
minecraftinfo/main.py
minecraftinfo-2.1.dist-info/METADATA
minecraftinfo-2.1.dist-info/WHEEL
minecraftinfo-2.1.dist-info/top_level.txt
minecraftinfo-2.1.dist-info/RECORD
