Metadata-Version: 2.1
Name: minecraftinfo
Version: 2.1
Summary: minecraftinfo is a library that allows you to get information about minecraft servers, skins, etc. in python
Author: naisu
License: MIT
